dj_cashier/__init__.py
dj_cashier/apps.py
dj_cashier/config.py
dj_cashier/migrations/0001_initial.py
dj_cashier/migrations/__init__.py
dj_cashier/models/__init__.py
dj_cashier/models/payment_method.py
dj_cashier/models/subscribable.py
dj_cashier/models/subscription.py
dj_cashier/models/subscription_Item.py
dj_cashier/urls.py
dj_cashier/utils.py
dj_cashier/views.py
dj_cashier-0.1.1.dist-info/AUTHORS.rst
dj_cashier-0.1.1.dist-info/METADATA
dj_cashier-0.1.1.dist-info/WHEEL
dj_cashier-0.1.1.dist-info/RECORD
