Metadata-Version: 2.1
Name: dj-cashier
Version: 0.1.1
Summary: Your project description goes here
Home-page: https://github.com/kaleemibnanwar/dj-cashier
License: MIT
Keywords: django,stripe,django-cashier,dj-cashier
Author: Kaleem ibn Anwar
Author-email: kaleemibnanwar@gmail.com
Classifier: License :: OSI Approved :: MIT License
Classifier: Programming Language :: Python :: 2
Classifier: Programming Language :: Python :: 2.7
Classifier: Programming Language :: Python :: 3
Classifier: Programming Language :: Python :: 3.4
Classifier: Programming Language :: Python :: 3.5
Classifier: Programming Language :: Python :: 3.6
Classifier: Programming Language :: Python :: 3.7
Classifier: Programming Language :: Python :: 3.8
Classifier: Programming Language :: Python :: 3.9
Classifier: Programming Language :: Python :: 3.10
Classifier: Programming Language :: Python :: 3.11
Classifier: Programming Language :: Python :: 3.12
Requires-Dist: django
Project-URL: Documentation, https://dj-cashier.readthedocs.io
Project-URL: Repository, https://github.com/kaleemibnanwar/dj-cashier
